whey/__init__.py
whey/__main__.py
whey/_editable.py
whey/additional_files.py
whey/builder.py
whey/foreman.py
whey/py.typed
whey/utils.py
whey/config/__init__.py
whey/config/pep621.py
whey/config/whey.py
whey-0.1.1.dist-info/LICENSE
whey-0.1.1.dist-info/METADATA
whey-0.1.1.dist-info/WHEEL
whey-0.1.1.dist-info/entry_points.txt
whey-0.1.1.dist-info/top_level.txt
whey-0.1.1.dist-info/RECORD
