Metadata-Version: 2.1
Name: whey
Version: 0.1.1
Summary: A simple Python wheel builder for simple projects.
Home-page: https://github.com/repo-helper/whey
Author: Dominic Davis-Foster
Author-email: Dominic Davis-Foster <dominic@davis-foster.co.uk>
License: Copyright (c) 2021 Dominic Davis-Foster
Project-URL: Homepage, https://github.com/repo-helper/whey
Project-URL: Issue Tracker, https://github.com/repo-helper/whey/issues
Project-URL: Source Code, https://github.com/repo-helper/whey
Project-URL: Documentation, https://whey.readthedocs.io/en/latest
Keywords: build,distribution,packaging,pep517,pep621,sdist,wheel
Platform: Windows
Platform: macOS
Platform: Linux
Classifier: Development Status :: 3 - Alpha
Classifier: Environment :: Console
Classifier: Intended Audience :: Developers
Classifier: License :: OSI Approved :: MIT License
Classifier: Operating System :: OS Independent
Classifier: Programming Language :: Python
Classifier: Programming Language :: Python :: 3 :: Only
Classifier: Programming Language :: Python :: 3.6
Classifier: Programming Language :: Python :: 3.7
Classifier: Programming Language :: Python :: 3.8
Classifier: Programming Language :: Python :: 3.9
Classifier: Programming Language :: Python :: 3.10
Classifier: Programming Language :: Python :: 3.11
Classifier: Programming Language :: Python :: 3.12
Classifier: Programming Language :: Python :: Implementation :: CPython
Classifier: Programming Language :: Python :: Implementation :: PyPy
Classifier: Topic :: Software Development :: Build Tools
Classifier: Topic :: Software Development :: Libraries :: Python Modules
Classifier: Topic :: System :: Archiving :: Packaging
Classifier: Typing :: Typed
Requires-Python: >=3.6.1
License-File: LICENSE
Requires-Dist: attrs >=22.2.0
Requires-Dist: click >=7.1.2
Requires-Dist: consolekit >=1.4.1
Requires-Dist: dist-meta >=0.1.0
Requires-Dist: dom-toml >=2.0.0
Requires-Dist: domdf-python-tools >=2.8.0
Requires-Dist: handy-archives >=0.2.0
Requires-Dist: natsort >=7.1.1
Requires-Dist: packaging >=20.9
Requires-Dist: pyproject-parser >=0.11.0
Requires-Dist: shippinglabel >=0.16.0
Provides-Extra: all
Requires-Dist: docutils >=0.16 ; extra == 'all'
Requires-Dist: editables >=0.2 ; extra == 'all'
Requires-Dist: pyproject-parser[readme] >=0.11.0b1 ; extra == 'all'
Provides-Extra: editable
Requires-Dist: editables >=0.2 ; extra == 'editable'
Provides-Extra: readme
Requires-Dist: docutils >=0.16 ; extra == 'readme'
Requires-Dist: pyproject-parser[readme] >=0.11.0b1 ; extra == 'readme'
